equid/__init__.py
equid/test.py
equid-0.1.2.dist-info/METADATA
equid-0.1.2.dist-info/WHEEL
equid-0.1.2.dist-info/top_level.txt
equid-0.1.2.dist-info/RECORD
